setup.cfg
setup.py
asyncinflux/__init__.py
asyncinflux.egg-info/PKG-INFO
asyncinflux.egg-info/SOURCES.txt
asyncinflux.egg-info/dependency_links.txt
asyncinflux.egg-info/requires.txt
asyncinflux.egg-info/top_level.txt
tests/__init__.py
tests/test_asyncinflux.py