Metadata-Version: 1.1
Name: asyncinflux
Version: 0.0.3
Summary: Uses codap to provide async influxdb
Home-page: https://github.com/lateefj/asyncinflux
Author: Lateef H. Jackson
Author-email: lateef.jackson@gmail.com
License: Apache License V2
Keywords: influxdb threading gevent eventlet coroutine
Platform: UNKNOWN
Classifier: Development Status :: 3 - Alpha
Classifier: Topic :: Utilities
Classifier: License :: OSI Approved :: BSD License
